LICENSE
README.md
setup.py
revampdeployer/__init__.py
revampdeployer/__main__.py
revampdeployer/deployer.py
revampdeployer.egg-info/PKG-INFO
revampdeployer.egg-info/SOURCES.txt
revampdeployer.egg-info/dependency_links.txt
revampdeployer.egg-info/entry_points.txt
revampdeployer.egg-info/top_level.txt