Metadata-Version: 2.1
Name: revampdeployer
Version: 0.1.4
License-File: LICENSE
